<AllKnows><Knows person='http://www.ic.unicamp.br/MC536/2013/1/andresantanche' colleague='http://www.ic.unicamp.br/MC536/2013/1/luizjunior'/><Knows person='http://www.ic.unicamp.br/MC536/2013/1/andresantanche' colleague='http://www.ic.unicamp.br/MC536/2013/1/augustomorgan'/><Knows person='http://www.ic.unicamp.br/MC536/2013/1/ivanfreitas' colleague='http://www.ic.unicamp.br/MC536/2013/1/alexandremedeiros'/><Knows person='http://www.ic.unicamp.br/MC536/2013/1/ivanfreitas' colleague='http://www.ic.unicamp.br/MC536/2013/1/brunocarvalho'/><Knows person='http://www.ic.unicamp.br/MC536/2013/1/ivanfreitas' colleague='http://www.ic.unicamp.br/MC536/2013/1/danielferreira'/><Knows person='http://www.ic.unicamp.br/MC536/2013/1/ivanfreitas' colleague='http://www.ic.unicamp.br/MC536/2013/1/fabiosartorato'/><Knows person='http://www.ic.unicamp.br/MC536/2013/1/ivanfreitas' colleague='http://www.ic.unicamp.br/MC536/2013/1/gabrielbertazi'/><Knows person='http://www.ic.unicamp.br/MC536/2013/1/ivanfreitas' colleague='http://www.ic.unicamp.br/MC536/2013/1/igornunes'/><Knows person='http://www.ic.unicamp.br/MC536/2013/1/ivanfreitas' colleague='http://www.ic.unicamp.br/MC536/2013/1/matheusboy'/><Knows person='http://www.ic.unicamp.br/MC536/2013/1/matheusboy' colleague='http://www.ic.unicamp.br/MC536/2013/1/alexandremedeiros'/><Knows person='http://www.ic.unicamp.br/MC536/2013/1/matheusboy' colleague='http://www.ic.unicamp.br/MC536/2013/1/andresantanche'/><Knows person='http://www.ic.unicamp.br/MC536/2013/1/matheusboy' colleague='http://www.ic.unicamp.br/MC536/2013/1/davidchazanas'/><Knows person='http://www.ic.unicamp.br/MC536/2013/1/matheusboy' colleague='http://www.ic.unicamp.br/MC536/2013/1/brunocarvalho'/><Knows person='http://www.ic.unicamp.br/MC536/2013/1/matheusboy' colleague='http://www.ic.unicamp.br/MC536/2013/1/gabrielbertazi'/><Knows person='http://www.ic.unicamp.br/MC536/2013/1/matheusboy' colleague='http://www.ic.unicamp.br/MC536/2013/1/gabrielsarraff'/><Knows person='http://www.ic.unicamp.br/MC536/2013/1/matheusboy' colleague='http://www.ic.unicamp.br/MC536/2013/1/guilhermeplatzeck'/><Knows person='http://www.ic.unicamp.br/MC536/2013/1/matheusboy' colleague='http://www.ic.unicamp.br/MC536/2013/1/ivanfilho'/><Knows person='http://www.ic.unicamp.br/MC536/2013/1/matheusboy' colleague='http://www.ic.unicamp.br/MC536/2013/1/ivanfreitas'/><Knows person='http://www.ic.unicamp.br/MC536/2013/1/matheusboy' colleague='http://www.ic.unicamp.br/MC536/2013/1/rafaelgouvea'/><Knows person='http://www.ic.unicamp.br/MC536/2013/1/matheusboy' colleague='http://www.ic.unicamp.br/MC536/2013/1/raissamachado'/><Knows person='http://www.ic.unicamp.br/MC536/2013/1/matheusboy' colleague='http://www.ic.unicamp.br/MC536/2013/1/henriquegonzales'/><Knows person='http://www.ic.unicamp.br/MC536/2013/1/matheusboy' colleague='http://www.ic.unicamp.br/MC536/2013/1/danielferreira'/><Knows person='http://www.ic.unicamp.br/MC536/2013/1/matheusboy' colleague='http://www.ic.unicamp.br/MC536/2013/1/lucaslima'/><Knows person='http://www.ic.unicamp.br/MC536/2013/1/ivanfilho' colleague='http://www.ic.unicamp.br/MC536/2013/1/matheusboy'/><Knows person='http://www.ic.unicamp.br/MC536/2013/1/ivanfilho' colleague='http://www.ic.unicamp.br/MC536/2013/1/rafaelgouvea'/><Knows person='http://www.ic.unicamp.br/MC536/2013/1/ivanfilho' colleague='http://www.ic.unicamp.br/MC536/2013/1/andresantanche'/><Knows person='http://www.ic.unicamp.br/MC536/2013/1/viniciusana' colleague='http://www.ic.unicamp.br/MC536/2013/1/amadeubonfante'/><Knows person='http://www.ic.unicamp.br/MC536/2013/1/fernandomassunari' colleague='http://www.ic.unicamp.br/MC536/2013/1/alexandrekunieda'/><Knows person='http://www.ic.unicamp.br/MC536/2013/1/viniciusana' colleague='http://www.ic.unicamp.br/MC536/2013/1/andreborba'/><Knows person='http://www.ic.unicamp.br/MC536/2013/1/fernandomassunari' colleague='http://www.ic.unicamp.br/MC536/2013/1/andrevasconcellos'/><Knows person='http://www.ic.unicamp.br/MC536/2013/1/fernandomassunari' colleague='http://www.ic.unicamp.br/MC536/2013/1/andresantanche'/><Knows person='http://www.ic.unicamp.br/MC536/2013/1/viniciusana' colleague='http://www.ic.unicamp.br/MC536/2013/1/emilioweber'/><Knows person='http://www.ic.unicamp.br/MC536/2013/1/fernandomassunari' colleague='http://www.ic.unicamp.br/MC536/2013/1/danielferreira'/><Knows person='http://www.ic.unicamp.br/MC536/2013/1/fernandomassunari' colleague='http://www.ic.unicamp.br/MC536/2013/1/eduardomendes'/><Knows person='http://www.ic.unicamp.br/MC536/2013/1/fernandomassunari' colleague='http://www.ic.unicamp.br/MC536/2013/1/felipeoliveira'/><Knows person='http://www.ic.unicamp.br/MC536/2013/1/marcelofabri' colleague='http://www.ic.unicamp.br/MC536/2013/1/paulorego'/><Knows person='http://www.ic.unicamp.br/MC536/2013/1/henriquegonzales' colleague='http://www.ic.unicamp.br/MC536/2013/1/andresantanche'/><Knows person='http://www.ic.unicamp.br/MC536/2013/1/viniciusana' colleague='http://www.ic.unicamp.br/MC536/2013/1/mariasousa'/><Knows person='http://www.ic.unicamp.br/MC536/2013/1/marcelofabri' colleague='http://www.ic.unicamp.br/MC536/2013/1/thiagopires'/><Knows person='http://www.ic.unicamp.br/MC536/2013/1/fernandomassunari' colleague='http://www.ic.unicamp.br/MC536/2013/1/henriquegonzales'/><Knows person='http://www.ic.unicamp.br/MC536/2013/1/marcelofabri' colleague='http://www.ic.unicamp.br/MC536/2013/1/guilhermenunes'/><Knows person='http://www.ic.unicamp.br/MC536/2013/1/henriquegonzales' colleague='http://www.ic.unicamp.br/MC536/2013/1/alexandrekunieda'/><Knows person='http://www.ic.unicamp.br/MC536/2013/1/viniciusana' colleague='http://www.ic.unicamp.br/MC536/2013/1/pedrofigueiredo'/><Knows person='http://www.ic.unicamp.br/MC536/2013/1/laisminchillo' colleague='http://www.ic.unicamp.br/MC536/2013/1/arthuralvarez'/><Knows person='http://www.ic.unicamp.br/MC536/2013/1/arthuralvarez' colleague='http://www.ic.unicamp.br/MC536/2013/1/laisminchillo'/><Knows person='http://www.ic.unicamp.br/MC536/2013/1/marcelofabri' colleague='http://www.ic.unicamp.br/MC536/2013/1/andrepaganini'/><Knows person='http://www.ic.unicamp.br/MC536/2013/1/fernandomassunari' colleague='http://www.ic.unicamp.br/MC536/2013/1/leonardoana'/><Knows person='http://www.ic.unicamp.br/MC536/2013/1/henriquegonzales' colleague='http://www.ic.unicamp.br/MC536/2013/1/danielferreira'/><Knows person='http://www.ic.unicamp.br/MC536/2013/1/marcelofabri' colleague='http://www.ic.unicamp.br/MC536/2013/1/luismendes'/><Knows person='http://www.ic.unicamp.br/MC536/2013/1/henriquegonzales' colleague='http://www.ic.unicamp.br/MC536/2013/1/fernandomassunari'/><Knows person='http://www.ic.unicamp.br/MC536/2013/1/fernandomassunari' colleague='http://www.ic.unicamp.br/MC536/2013/1/marcelozabani'/><Knows person='http://www.ic.unicamp.br/MC536/2013/1/viniciusana' colleague='http://www.ic.unicamp.br/MC536/2013/1/raphaelsantos'/><Knows person='http://www.ic.unicamp.br/MC536/2013/1/marcelofabri' colleague='http://www.ic.unicamp.br/MC536/2013/1/rafaelsacchi'/><Knows person='http://www.ic.unicamp.br/MC536/2013/1/fernandomassunari' colleague='http://www.ic.unicamp.br/MC536/2013/1/luizjunior'/><Knows person='http://www.ic.unicamp.br/MC536/2013/1/henriquegonzales' colleague='http://www.ic.unicamp.br/MC536/2013/1/gabrielsarraff'/><Knows person='http://www.ic.unicamp.br/MC536/2013/1/marcelofabri' colleague='http://www.ic.unicamp.br/MC536/2013/1/lucasmadureira'/><Knows person='http://www.ic.unicamp.br/MC536/2013/1/viniciusana' colleague='http://www.ic.unicamp.br/MC536/2013/1/arthuralvarez'/><Knows person='http://www.ic.unicamp.br/MC536/2013/1/henriquegonzales' colleague='http://www.ic.unicamp.br/MC536/2013/1/lucasnakata'/><Knows person='http://www.ic.unicamp.br/MC536/2013/1/fernandomassunari' colleague='http://www.ic.unicamp.br/MC536/2013/1/thiagobalbo'/><Knows person='http://www.ic.unicamp.br/MC536/2013/1/henriquegonzales' colleague='http://www.ic.unicamp.br/MC536/2013/1/matheusboy'/><Knows person='http://www.ic.unicamp.br/MC536/2013/1/viniciussantos' colleague='http://www.ic.unicamp.br/MC536/2013/1/henriquegonzales'/><Knows person='http://www.ic.unicamp.br/MC536/2013/1/viniciusana' colleague='http://www.ic.unicamp.br/MC536/2013/1/gustavosilva'/><Knows person='http://www.ic.unicamp.br/MC536/2013/1/henriquegonzales' colleague='http://www.ic.unicamp.br/MC536/2013/1/thiagobalbo'/><Knows person='http://www.ic.unicamp.br/MC536/2013/1/henriquegonzales' colleague='http://www.ic.unicamp.br/MC536/2013/1/viniciussantos'/><Knows person='http://www.ic.unicamp.br/MC536/2013/1/viniciussantos' colleague='http://www.ic.unicamp.br/MC536/2013/1/andreborba'/><Knows person='http://www.ic.unicamp.br/MC536/2013/1/lucaslima' colleague='http://www.ic.unicamp.br/MC536/2013/1/brunocarvalho'/><Knows person='http://www.ic.unicamp.br/MC536/2013/1/leonardoana' colleague='http://www.ic.unicamp.br/MC536/2013/1/andresantanche'/><Knows person='http://www.ic.unicamp.br/MC536/2013/1/lucaslima' colleague='http://www.ic.unicamp.br/MC536/2013/1/diegorubini'/><Knows person='http://www.ic.unicamp.br/MC536/2013/1/brunocarvalho' colleague='http://www.ic.unicamp.br/MC536/2013/1/alexandremedeiros'/><Knows person='http://www.ic.unicamp.br/MC536/2013/1/lucaslima' colleague='http://www.ic.unicamp.br/MC536/2013/1/raissamachado'/><Knows person='http://www.ic.unicamp.br/MC536/2013/1/viniciussantos' colleague='http://www.ic.unicamp.br/MC536/2013/1/andresantanche'/><Knows person='http://www.ic.unicamp.br/MC536/2013/1/henriquegonzales' colleague='http://www.ic.unicamp.br/MC536/2013/1/leonardoana'/><Knows person='http://www.ic.unicamp.br/MC536/2013/1/lucaslima' colleague='http://www.ic.unicamp.br/MC536/2013/1/renatovargas'/><Knows person='http://www.ic.unicamp.br/MC536/2013/1/brunocarvalho' colleague='http://www.ic.unicamp.br/MC536/2013/1/andresantanche'/><Knows person='http://www.ic.unicamp.br/MC536/2013/1/lucaslima' colleague='http://www.ic.unicamp.br/MC536/2013/1/matheusboy'/><Knows person='http://www.ic.unicamp.br/MC536/2013/1/leonardoana' colleague='http://www.ic.unicamp.br/MC536/2013/1/alexandrekunieda'/><Knows person='http://www.ic.unicamp.br/MC536/2013/1/henriquegonzales' colleague='http://www.ic.unicamp.br/MC536/2013/1/marcelozabani'/><Knows person='http://www.ic.unicamp.br/MC536/2013/1/leonardoana' colleague='http://www.ic.unicamp.br/MC536/2013/1/danielferreira'/><Knows person='http://www.ic.unicamp.br/MC536/2013/1/brunocarvalho' colleague='http://www.ic.unicamp.br/MC536/2013/1/augustomorgan'/><Knows person='http://www.ic.unicamp.br/MC536/2013/1/pedroalves' colleague='http://www.ic.unicamp.br/MC536/2013/1/eduardohitomi'/><Knows person='http://www.ic.unicamp.br/MC536/2013/1/leonardoana' colleague='http://www.ic.unicamp.br/MC536/2013/1/eduardomendes'/><Knows person='http://www.ic.unicamp.br/MC536/2013/1/fabiosartorato' colleague='http://www.ic.unicamp.br/MC536/2013/1/alexandremedeiros'/><Knows person='http://www.ic.unicamp.br/MC536/2013/1/brunocarvalho' colleague='http://www.ic.unicamp.br/MC536/2013/1/diegorubini'/><Knows person='http://www.ic.unicamp.br/MC536/2013/1/leonardoana' colleague='http://www.ic.unicamp.br/MC536/2013/1/felipeoliveira'/><Knows person='http://www.ic.unicamp.br/MC536/2013/1/fabiosartorato' colleague='http://www.ic.unicamp.br/MC536/2013/1/andresantanche'/><Knows person='http://www.ic.unicamp.br/MC536/2013/1/leonardoana' colleague='http://www.ic.unicamp.br/MC536/2013/1/fernandomassunari'/><Knows person='http://www.ic.unicamp.br/MC536/2013/1/augustomorgan' colleague='http://www.ic.unicamp.br/MC536/2013/1/alexandremedeiros'/><Knows person='http://www.ic.unicamp.br/MC536/2013/1/brunocarvalho' colleague='http://www.ic.unicamp.br/MC536/2013/1/renatovargas'/><Knows person='http://www.ic.unicamp.br/MC536/2013/1/leonardoana' colleague='http://www.ic.unicamp.br/MC536/2013/1/gabrielsarraff'/><Knows person='http://www.ic.unicamp.br/MC536/2013/1/augustomorgan' colleague='http://www.ic.unicamp.br/MC536/2013/1/andresantanche'/><Knows person='http://www.ic.unicamp.br/MC536/2013/1/brunocarvalho' colleague='http://www.ic.unicamp.br/MC536/2013/1/emilioweber'/><Knows person='http://www.ic.unicamp.br/MC536/2013/1/fabiosartorato' colleague='http://www.ic.unicamp.br/MC536/2013/1/augustomorgan'/><Knows person='http://www.ic.unicamp.br/MC536/2013/1/leonardoana' colleague='http://www.ic.unicamp.br/MC536/2013/1/lucasnakata'/><Knows person='http://www.ic.unicamp.br/MC536/2013/1/augustomorgan' colleague='http://www.ic.unicamp.br/MC536/2013/1/brunocarvalho'/><Knows person='http://www.ic.unicamp.br/MC536/2013/1/fabiosartorato' colleague='http://www.ic.unicamp.br/MC536/2013/1/brunocarvalho'/><Knows person='http://www.ic.unicamp.br/MC536/2013/1/leonardoana' colleague='http://www.ic.unicamp.br/MC536/2013/1/henriquegonzales'/><Knows person='http://www.ic.unicamp.br/MC536/2013/1/augustomorgan' colleague='http://www.ic.unicamp.br/MC536/2013/1/fabiosartorato'/><Knows person='http://www.ic.unicamp.br/MC536/2013/1/brunocarvalho' colleague='http://www.ic.unicamp.br/MC536/2013/1/fabiosartorato'/><Knows person='http://www.ic.unicamp.br/MC536/2013/1/fabiosartorato' colleague='http://www.ic.unicamp.br/MC536/2013/1/arthuralvarez'/><Knows person='http://www.ic.unicamp.br/MC536/2013/1/augustomorgan' colleague='http://www.ic.unicamp.br/MC536/2013/1/emilioweber'/><Knows person='http://www.ic.unicamp.br/MC536/2013/1/brunocarvalho' colleague='http://www.ic.unicamp.br/MC536/2013/1/gabrielbertazi'/><Knows person='http://www.ic.unicamp.br/MC536/2013/1/augustomorgan' colleague='http://www.ic.unicamp.br/MC536/2013/1/gabrielbertazi'/><Knows person='http://www.ic.unicamp.br/MC536/2013/1/fabiosartorato' colleague='http://www.ic.unicamp.br/MC536/2013/1/emilioweber'/><Knows person='http://www.ic.unicamp.br/MC536/2013/1/leonardoana' colleague='http://www.ic.unicamp.br/MC536/2013/1/raissamachado'/><Knows person='http://www.ic.unicamp.br/MC536/2013/1/brunocarvalho' colleague='http://www.ic.unicamp.br/MC536/2013/1/ivanfreitas'/><Knows person='http://www.ic.unicamp.br/MC536/2013/1/rafaelgouvea' colleague='http://www.ic.unicamp.br/MC536/2013/1/alexandremedeiros'/><Knows person='http://www.ic.unicamp.br/MC536/2013/1/fabiosartorato' colleague='http://www.ic.unicamp.br/MC536/2013/1/gabrielbertazi'/><Knows person='http://www.ic.unicamp.br/MC536/2013/1/leonardoana' colleague='http://www.ic.unicamp.br/MC536/2013/1/thiagobalbo'/><Knows person='http://www.ic.unicamp.br/MC536/2013/1/rafaelgouvea' colleague='http://www.ic.unicamp.br/MC536/2013/1/andresantanche'/><Knows person='http://www.ic.unicamp.br/MC536/2013/1/fabiosartorato' colleague='http://www.ic.unicamp.br/MC536/2013/1/gustavosilva'/><Knows person='http://www.ic.unicamp.br/MC536/2013/1/brunocarvalho' colleague='http://www.ic.unicamp.br/MC536/2013/1/guilhermeplatzeck'/><Knows person='http://www.ic.unicamp.br/MC536/2013/1/rafaelgouvea' colleague='http://www.ic.unicamp.br/MC536/2013/1/danielferreira'/><Knows person='http://www.ic.unicamp.br/MC536/2013/1/augustomorgan' colleague='http://www.ic.unicamp.br/MC536/2013/1/ivanfreitas'/><Knows person='http://www.ic.unicamp.br/MC536/2013/1/fabiosartorato' colleague='http://www.ic.unicamp.br/MC536/2013/1/ivanfreitas'/><Knows person='http://www.ic.unicamp.br/MC536/2013/1/brunocarvalho' colleague='http://www.ic.unicamp.br/MC536/2013/1/jonatanvalongo'/><Knows person='http://www.ic.unicamp.br/MC536/2013/1/rafaelgouvea' colleague='http://www.ic.unicamp.br/MC536/2013/1/davidchazanas'/><Knows person='http://www.ic.unicamp.br/MC536/2013/1/fabiosartorato' colleague='http://www.ic.unicamp.br/MC536/2013/1/jonatanvalongo'/><Knows person='http://www.ic.unicamp.br/MC536/2013/1/augustomorgan' colleague='http://www.ic.unicamp.br/MC536/2013/1/jonatanvalongo'/><Knows person='http://www.ic.unicamp.br/MC536/2013/1/fabiosartorato' colleague='http://www.ic.unicamp.br/MC536/2013/1/laisminchillo'/><Knows person='http://www.ic.unicamp.br/MC536/2013/1/augustomorgan' colleague='http://www.ic.unicamp.br/MC536/2013/1/rafaelhermano'/><Knows person='http://www.ic.unicamp.br/MC536/2013/1/brunocarvalho' colleague='http://www.ic.unicamp.br/MC536/2013/1/lucaslima'/><Knows person='http://www.ic.unicamp.br/MC536/2013/1/fabiosartorato' colleague='http://www.ic.unicamp.br/MC536/2013/1/guilhermeplatzeck'/><Knows person='http://www.ic.unicamp.br/MC536/2013/1/rafaelgouvea' colleague='http://www.ic.unicamp.br/MC536/2013/1/ivanfilho'/><Knows person='http://www.ic.unicamp.br/MC536/2013/1/brunocarvalho' colleague='http://www.ic.unicamp.br/MC536/2013/1/rafaelsacchi'/><Knows person='http://www.ic.unicamp.br/MC536/2013/1/rafaelgouvea' colleague='http://www.ic.unicamp.br/MC536/2013/1/ivanfreitas'/><Knows person='http://www.ic.unicamp.br/MC536/2013/1/augustomorgan' colleague='http://www.ic.unicamp.br/MC536/2013/1/andreborba'/><Knows person='http://www.ic.unicamp.br/MC536/2013/1/fabiosartorato' colleague='http://www.ic.unicamp.br/MC536/2013/1/luismendes'/><Knows person='http://www.ic.unicamp.br/MC536/2013/1/brunocarvalho' colleague='http://www.ic.unicamp.br/MC536/2013/1/raphaelsantos'/><Knows person='http://www.ic.unicamp.br/MC536/2013/1/rafaelgouvea' colleague='http://www.ic.unicamp.br/MC536/2013/1/mariasousa'/><Knows person='http://www.ic.unicamp.br/MC536/2013/1/augustomorgan' colleague='http://www.ic.unicamp.br/MC536/2013/1/guilhermeplatzeck'/><Knows person='http://www.ic.unicamp.br/MC536/2013/1/rafaelgouvea' colleague='http://www.ic.unicamp.br/MC536/2013/1/matheusboy'/><Knows person='http://www.ic.unicamp.br/MC536/2013/1/augustomorgan' colleague='http://www.ic.unicamp.br/MC536/2013/1/guilhermenunes'/><Knows person='http://www.ic.unicamp.br/MC536/2013/1/brunocarvalho' colleague='http://www.ic.unicamp.br/MC536/2013/1/laisminchillo'/><Knows person='http://www.ic.unicamp.br/MC536/2013/1/fabiosartorato' colleague='http://www.ic.unicamp.br/MC536/2013/1/thiagopires'/><Knows person='http://www.ic.unicamp.br/MC536/2013/1/augustomorgan' colleague='http://www.ic.unicamp.br/MC536/2013/1/gustavosilva'/><Knows person='http://www.ic.unicamp.br/MC536/2013/1/rafaelgouvea' colleague='http://www.ic.unicamp.br/MC536/2013/1/raissamachado'/><Knows person='http://www.ic.unicamp.br/MC536/2013/1/brunocarvalho' colleague='http://www.ic.unicamp.br/MC536/2013/1/luizjunior'/><Knows person='http://www.ic.unicamp.br/MC536/2013/1/augustomorgan' colleague='http://www.ic.unicamp.br/MC536/2013/1/lucasmadureira'/><Knows person='http://www.ic.unicamp.br/MC536/2013/1/augustomorgan' colleague='http://www.ic.unicamp.br/MC536/2013/1/luismendes'/><Knows person='http://www.ic.unicamp.br/MC536/2013/1/brunocarvalho' colleague='http://www.ic.unicamp.br/MC536/2013/1/rafaelhermano'/><Knows person='http://www.ic.unicamp.br/MC536/2013/1/augustomorgan' colleague='http://www.ic.unicamp.br/MC536/2013/1/mariasousa'/><Knows person='http://www.ic.unicamp.br/MC536/2013/1/augustomorgan' colleague='http://www.ic.unicamp.br/MC536/2013/1/paulorego'/><Knows person='http://www.ic.unicamp.br/MC536/2013/1/augustomorgan' colleague='http://www.ic.unicamp.br/MC536/2013/1/raphaelsantos'/><Knows person='http://www.ic.unicamp.br/MC536/2013/1/jonatanvalongo' colleague='http://www.ic.unicamp.br/MC536/2013/1/alexandremedeiros'/><Knows person='http://www.ic.unicamp.br/MC536/2013/1/jonatanvalongo' colleague='http://www.ic.unicamp.br/MC536/2013/1/augustomorgan'/><Knows person='http://www.ic.unicamp.br/MC536/2013/1/jonatanvalongo' colleague='http://www.ic.unicamp.br/MC536/2013/1/brunocarvalho'/><Knows person='http://www.ic.unicamp.br/MC536/2013/1/jonatanvalongo' colleague='http://www.ic.unicamp.br/MC536/2013/1/fabiosartorato'/><Knows person='http://www.ic.unicamp.br/MC536/2013/1/jonatanvalongo' colleague='http://www.ic.unicamp.br/MC536/2013/1/gabrielbertazi'/><Knows person='http://www.ic.unicamp.br/MC536/2013/1/lucasmadureira' colleague='http://www.ic.unicamp.br/MC536/2013/1/andrepaganini'/><Knows person='http://www.ic.unicamp.br/MC536/2013/1/jonatanvalongo' colleague='http://www.ic.unicamp.br/MC536/2013/1/emilioweber'/><Knows person='http://www.ic.unicamp.br/MC536/2013/1/jonatanvalongo' colleague='http://www.ic.unicamp.br/MC536/2013/1/mariasousa'/><Knows person='http://www.ic.unicamp.br/MC536/2013/1/lucasmadureira' colleague='http://www.ic.unicamp.br/MC536/2013/1/augustomorgan'/><Knows person='http://www.ic.unicamp.br/MC536/2013/1/jonatanvalongo' colleague='http://www.ic.unicamp.br/MC536/2013/1/guilhermenunes'/><Knows person='http://www.ic.unicamp.br/MC536/2013/1/guilhermenunes' colleague='http://www.ic.unicamp.br/MC536/2013/1/alexandremedeiros'/><Knows person='http://www.ic.unicamp.br/MC536/2013/1/guilhermenunes' colleague='http://www.ic.unicamp.br/MC536/2013/1/amadeubonfante'/><Knows person='http://www.ic.unicamp.br/MC536/2013/1/guilhermenunes' colleague='http://www.ic.unicamp.br/MC536/2013/1/andrepaganini'/><Knows person='http://www.ic.unicamp.br/MC536/2013/1/lucasmadureira' colleague='http://www.ic.unicamp.br/MC536/2013/1/guilhermenunes'/><Knows person='http://www.ic.unicamp.br/MC536/2013/1/guilhermenunes' colleague='http://www.ic.unicamp.br/MC536/2013/1/paulorego'/><Knows person='http://www.ic.unicamp.br/MC536/2013/1/lucasmadureira' colleague='http://www.ic.unicamp.br/MC536/2013/1/jonatanvalongo'/><Knows person='http://www.ic.unicamp.br/MC536/2013/1/guilhermenunes' colleague='http://www.ic.unicamp.br/MC536/2013/1/thiagopires'/><Knows person='http://www.ic.unicamp.br/MC536/2013/1/guilhermenunes' colleague='http://www.ic.unicamp.br/MC536/2013/1/rafaelsacchi'/><Knows person='http://www.ic.unicamp.br/MC536/2013/1/guilhermenunes' colleague='http://www.ic.unicamp.br/MC536/2013/1/luismendes'/><Knows person='http://www.ic.unicamp.br/MC536/2013/1/lucasmadureira' colleague='http://www.ic.unicamp.br/MC536/2013/1/marcelofabri'/><Knows person='http://www.ic.unicamp.br/MC536/2013/1/paulorego' colleague='http://www.ic.unicamp.br/MC536/2013/1/guilhermenunes'/><Knows person='http://www.ic.unicamp.br/MC536/2013/1/lucasmadureira' colleague='http://www.ic.unicamp.br/MC536/2013/1/paulorego'/><Knows person='http://www.ic.unicamp.br/MC536/2013/1/guilhermenunes' colleague='http://www.ic.unicamp.br/MC536/2013/1/jonatanvalongo'/><Knows person='http://www.ic.unicamp.br/MC536/2013/1/paulorego' colleague='http://www.ic.unicamp.br/MC536/2013/1/luismendes'/><Knows person='http://www.ic.unicamp.br/MC536/2013/1/guilhermenunes' colleague='http://www.ic.unicamp.br/MC536/2013/1/marcelofabri'/><Knows person='http://www.ic.unicamp.br/MC536/2013/1/lucasmadureira' colleague='http://www.ic.unicamp.br/MC536/2013/1/rafaelsacchi'/><Knows person='http://www.ic.unicamp.br/MC536/2013/1/paulorego' colleague='http://www.ic.unicamp.br/MC536/2013/1/marcelofabri'/><Knows person='http://www.ic.unicamp.br/MC536/2013/1/paulorego' colleague='http://www.ic.unicamp.br/MC536/2013/1/andrepaganini'/><Knows person='http://www.ic.unicamp.br/MC536/2013/1/paulorego' colleague='http://www.ic.unicamp.br/MC536/2013/1/thiagopires'/><Knows person='http://www.ic.unicamp.br/MC536/2013/1/paulorego' colleague='http://www.ic.unicamp.br/MC536/2013/1/lucasmadureira'/><Knows person='http://www.ic.unicamp.br/MC536/2013/1/lucasmadureira' colleague='http://www.ic.unicamp.br/MC536/2013/1/renatovargas'/><Knows person='http://www.ic.unicamp.br/MC536/2013/1/paulorego' colleague='http://www.ic.unicamp.br/MC536/2013/1/rafaelsacchi'/><Knows person='http://www.ic.unicamp.br/MC536/2013/1/jonatanvalongo' colleague='http://www.ic.unicamp.br/MC536/2013/1/paulorego'/><Knows person='http://www.ic.unicamp.br/MC536/2013/1/jonatanvalongo' colleague='http://www.ic.unicamp.br/MC536/2013/1/thiagopires'/><Knows person='http://www.ic.unicamp.br/MC536/2013/1/eduardohitomi' colleague='http://www.ic.unicamp.br/MC536/2013/1/pedroalves'/><Knows person='http://www.ic.unicamp.br/MC536/2013/1/eduardohitomi' colleague='http://www.ic.unicamp.br/MC536/2013/1/andresantanche'/><Knows person='http://www.ic.unicamp.br/MC536/2013/1/eduardohitomi' colleague='http://www.ic.unicamp.br/MC536/2013/1/luismendes'/><Knows person='http://www.ic.unicamp.br/MC536/2013/1/andreborba' colleague='http://www.ic.unicamp.br/MC536/2013/1/viniciussantos'/><Knows person='http://www.ic.unicamp.br/MC536/2013/1/andreborba' colleague='http://www.ic.unicamp.br/MC536/2013/1/amadeubonfante'/><Knows person='http://www.ic.unicamp.br/MC536/2013/1/andreborba' colleague='http://www.ic.unicamp.br/MC536/2013/1/fabiosartorato'/><Knows person='http://www.ic.unicamp.br/MC536/2013/1/andreborba' colleague='http://www.ic.unicamp.br/MC536/2013/1/arthuralvarez'/><Knows person='http://www.ic.unicamp.br/MC536/2013/1/andreborba' colleague='http://www.ic.unicamp.br/MC536/2013/1/raphaelsantos'/><Knows person='http://www.ic.unicamp.br/MC536/2013/1/andreborba' colleague='http://www.ic.unicamp.br/MC536/2013/1/brunocarvalho'/><Knows person='http://www.ic.unicamp.br/MC536/2013/1/andreborba' colleague='http://www.ic.unicamp.br/MC536/2013/1/emilioweber'/><Knows person='http://www.ic.unicamp.br/MC536/2013/1/andreborba' colleague='http://www.ic.unicamp.br/MC536/2013/1/mariasousa'/><Knows person='http://www.ic.unicamp.br/MC536/2013/1/andreborba' colleague='http://www.ic.unicamp.br/MC536/2013/1/viniciusana'/><Knows person='http://www.ic.unicamp.br/MC536/2013/1/renatovargas' colleague='http://www.ic.unicamp.br/MC536/2013/1/lucaslima'/><Knows person='http://www.ic.unicamp.br/MC536/2013/1/renatovargas' colleague='http://www.ic.unicamp.br/MC536/2013/1/alexandremedeiros'/><Knows person='http://www.ic.unicamp.br/MC536/2013/1/renatovargas' colleague='http://www.ic.unicamp.br/MC536/2013/1/diegorubini'/><Knows person='http://www.ic.unicamp.br/MC536/2013/1/renatovargas' colleague='http://www.ic.unicamp.br/MC536/2013/1/raissamachado'/><Knows person='http://www.ic.unicamp.br/MC536/2013/1/renatovargas' colleague='http://www.ic.unicamp.br/MC536/2013/1/lucasmadureira'/><Knows person='http://www.ic.unicamp.br/MC536/2013/1/renatovargas' colleague='http://www.ic.unicamp.br/MC536/2013/1/andresantanche'/><Knows person='http://www.ic.unicamp.br/MC536/2013/1/renatovargas' colleague='http://www.ic.unicamp.br/MC536/2013/1/brunocarvalho'/><Knows person='http://www.ic.unicamp.br/MC536/2013/1/renatovargas' colleague='http://www.ic.unicamp.br/MC536/2013/1/matheusboy'/><Knows person='http://www.ic.unicamp.br/MC536/2013/1/pedrofigueiredo' colleague='http://www.ic.unicamp.br/MC536/2013/1/viniciusana'/><Knows person='http://www.ic.unicamp.br/MC536/2013/1/pedrofigueiredo' colleague='http://www.ic.unicamp.br/MC536/2013/1/arthuralvarez'/><Knows person='http://www.ic.unicamp.br/MC536/2013/1/pedrofigueiredo' colleague='http://www.ic.unicamp.br/MC536/2013/1/amadeubonfante'/><Knows person='http://www.ic.unicamp.br/MC536/2013/1/pedrofigueiredo' colleague='http://www.ic.unicamp.br/MC536/2013/1/emilioweber'/><Knows person='http://www.ic.unicamp.br/MC536/2013/1/pedrofigueiredo' colleague='http://www.ic.unicamp.br/MC536/2013/1/gustavosilva'/><Knows person='http://www.ic.unicamp.br/MC536/2013/1/pedrofigueiredo' colleague='http://www.ic.unicamp.br/MC536/2013/1/mariasousa'/><Knows person='http://www.ic.unicamp.br/MC536/2013/1/pedrofigueiredo' colleague='http://www.ic.unicamp.br/MC536/2013/1/raphaelsantos'/><Knows person='http://www.ic.unicamp.br/MC536/2013/1/pedrofigueiredo' colleague='http://www.ic.unicamp.br/MC536/2013/1/andreborba'/><Knows person='http://www.ic.unicamp.br/MC536/2013/1/pedrofigueiredo' colleague='http://www.ic.unicamp.br/MC536/2013/1/rafaelsacchi'/><Knows person='http://www.ic.unicamp.br/MC536/2013/1/pedrofigueiredo' colleague='http://www.ic.unicamp.br/MC536/2013/1/andrepaganini'/><Knows person='http://www.ic.unicamp.br/MC536/2013/1/pedrofigueiredo' colleague='http://www.ic.unicamp.br/MC536/2013/1/fabiosartorato'/><Knows person='http://www.ic.unicamp.br/MC536/2013/1/pedrofigueiredo' colleague='http://www.ic.unicamp.br/MC536/2013/1/brunocarvalho'/><Knows person='http://www.ic.unicamp.br/MC536/2013/1/pedrofigueiredo' colleague='http://www.ic.unicamp.br/MC536/2013/1/alexandremedeiros'/><Knows person='http://www.ic.unicamp.br/MC536/2013/1/pedrofigueiredo' colleague='http://www.ic.unicamp.br/MC536/2013/1/andresantanche'/><Knows person='http://www.ic.unicamp.br/MC536/2013/1/pedrofigueiredo' colleague='http://www.ic.unicamp.br/MC536/2013/1/luizjunior'/><Knows person='http://www.ic.unicamp.br/MC536/2013/1/viniciusana' colleague='http://www.ic.unicamp.br/MC536/2013/1/guilhermeplatzeck'/><Knows person='http://www.ic.unicamp.br/MC536/2013/1/alexandrekunieda' colleague='http://www.ic.unicamp.br/MC536/2013/1/felipeoliveira'/><Knows person='http://www.ic.unicamp.br/MC536/2013/1/alexandrekunieda' colleague='http://www.ic.unicamp.br/MC536/2013/1/marcelozabani'/><Knows person='http://www.ic.unicamp.br/MC536/2013/1/alexandrekunieda' colleague='http://www.ic.unicamp.br/MC536/2013/1/andreborba'/><Knows person='http://www.ic.unicamp.br/MC536/2013/1/alexandrekunieda' colleague='http://www.ic.unicamp.br/MC536/2013/1/fernandomassunari'/><Knows person='http://www.ic.unicamp.br/MC536/2013/1/alexandrekunieda' colleague='http://www.ic.unicamp.br/MC536/2013/1/leonardoana'/><Knows person='http://www.ic.unicamp.br/MC536/2013/1/alexandrekunieda' colleague='http://www.ic.unicamp.br/MC536/2013/1/raphaelsantos'/><Knows person='http://www.ic.unicamp.br/MC536/2013/1/eduardomendes' colleague='http://www.ic.unicamp.br/MC536/2013/1/fernandomassunari'/><Knows person='http://www.ic.unicamp.br/MC536/2013/1/eduardomendes' colleague='http://www.ic.unicamp.br/MC536/2013/1/leonardoana'/><Knows person='http://www.ic.unicamp.br/MC536/2013/1/henriquegonzales' colleague='http://www.ic.unicamp.br/MC536/2013/1/felipeoliveira'/><Knows person='http://www.ic.unicamp.br/MC536/2013/1/gabrielbertazi' colleague='http://www.ic.unicamp.br/MC536/2013/1/alexandremedeiros'/><Knows person='http://www.ic.unicamp.br/MC536/2013/1/gabrielbertazi' colleague='http://www.ic.unicamp.br/MC536/2013/1/augustomorgan'/><Knows person='http://www.ic.unicamp.br/MC536/2013/1/gabrielbertazi' colleague='http://www.ic.unicamp.br/MC536/2013/1/brunocarvalho'/><Knows person='http://www.ic.unicamp.br/MC536/2013/1/gabrielbertazi' colleague='http://www.ic.unicamp.br/MC536/2013/1/fabiosartorato'/><Knows person='http://www.ic.unicamp.br/MC536/2013/1/gabrielbertazi' colleague='http://www.ic.unicamp.br/MC536/2013/1/ivanfreitas'/><Knows person='http://www.ic.unicamp.br/MC536/2013/1/gabrielbertazi' colleague='http://www.ic.unicamp.br/MC536/2013/1/rafaelhermano'/><Knows person='http://www.ic.unicamp.br/MC536/2013/1/alexandremedeiros' colleague='http://www.ic.unicamp.br/MC536/2013/1/brunocarvalho'/><Knows person='http://www.ic.unicamp.br/MC536/2013/1/alexandremedeiros' colleague='http://www.ic.unicamp.br/MC536/2013/1/augustomorgan'/><Knows person='http://www.ic.unicamp.br/MC536/2013/1/alexandremedeiros' colleague='http://www.ic.unicamp.br/MC536/2013/1/gabrielbertazi'/><Knows person='http://www.ic.unicamp.br/MC536/2013/1/alexandremedeiros' colleague='http://www.ic.unicamp.br/MC536/2013/1/ivanfreitas'/><Knows person='http://www.ic.unicamp.br/MC536/2013/1/alexandremedeiros' colleague='http://www.ic.unicamp.br/MC536/2013/1/renatovargas'/><Knows person='http://www.ic.unicamp.br/MC536/2013/1/alexandremedeiros' colleague='http://www.ic.unicamp.br/MC536/2013/1/guilhermeplatzeck'/><Knows person='http://www.ic.unicamp.br/MC536/2013/1/alexandremedeiros' colleague='http://www.ic.unicamp.br/MC536/2013/1/matheusboy'/><Knows person='http://www.ic.unicamp.br/MC536/2013/1/felipeoliveira' colleague='http://www.ic.unicamp.br/MC536/2013/1/alexandrekunieda'/><Knows person='http://www.ic.unicamp.br/MC536/2013/1/lucasnakata' colleague='http://www.ic.unicamp.br/MC536/2013/1/igornunes'/><Knows person='http://www.ic.unicamp.br/MC536/2013/1/lucasnakata' colleague='http://www.ic.unicamp.br/MC536/2013/1/gabrielsarraff'/><Knows person='http://www.ic.unicamp.br/MC536/2013/1/lucasnakata' colleague='http://www.ic.unicamp.br/MC536/2013/1/danielferreira'/><Knows person='http://www.ic.unicamp.br/MC536/2013/1/gustavosilva' colleague='http://www.ic.unicamp.br/MC536/2013/1/amadeubonfante'/><Knows person='http://www.ic.unicamp.br/MC536/2013/1/felipeoliveira' colleague='http://www.ic.unicamp.br/MC536/2013/1/fernandomassunari'/><Knows person='http://www.ic.unicamp.br/MC536/2013/1/felipeoliveira' colleague='http://www.ic.unicamp.br/MC536/2013/1/henriquegonzales'/><Knows person='http://www.ic.unicamp.br/MC536/2013/1/marcelozabani' colleague='http://www.ic.unicamp.br/MC536/2013/1/alexandrekunieda'/><Knows person='http://www.ic.unicamp.br/MC536/2013/1/marcelozabani' colleague='http://www.ic.unicamp.br/MC536/2013/1/amadeubonfante'/><Knows person='http://www.ic.unicamp.br/MC536/2013/1/marcelozabani' colleague='http://www.ic.unicamp.br/MC536/2013/1/danielferreira'/><Knows person='http://www.ic.unicamp.br/MC536/2013/1/marcelozabani' colleague='http://www.ic.unicamp.br/MC536/2013/1/andrevasconcellos'/><Knows person='http://www.ic.unicamp.br/MC536/2013/1/marcelozabani' colleague='http://www.ic.unicamp.br/MC536/2013/1/fernandomassunari'/><Knows person='http://www.ic.unicamp.br/MC536/2013/1/marcelozabani' colleague='http://www.ic.unicamp.br/MC536/2013/1/thiagobalbo'/><Knows person='http://www.ic.unicamp.br/MC536/2013/1/marcelozabani' colleague='http://www.ic.unicamp.br/MC536/2013/1/leonardoana'/><Knows person='http://www.ic.unicamp.br/MC536/2013/1/andrevasconcellos' colleague='http://www.ic.unicamp.br/MC536/2013/1/marcelozabani'/><Knows person='http://www.ic.unicamp.br/MC536/2013/1/amadeubonfante' colleague='http://www.ic.unicamp.br/MC536/2013/1/andreborba'/><Knows person='http://www.ic.unicamp.br/MC536/2013/1/amadeubonfante' colleague='http://www.ic.unicamp.br/MC536/2013/1/viniciusana'/><Knows person='http://www.ic.unicamp.br/MC536/2013/1/amadeubonfante' colleague='http://www.ic.unicamp.br/MC536/2013/1/arthuralvarez'/><Knows person='http://www.ic.unicamp.br/MC536/2013/1/amadeubonfante' colleague='http://www.ic.unicamp.br/MC536/2013/1/emilioweber'/><Knows person='http://www.ic.unicamp.br/MC536/2013/1/viniciusana' colleague='http://www.ic.unicamp.br/MC536/2013/1/fabiosartorato'/><Knows person='http://www.ic.unicamp.br/MC536/2013/1/amadeubonfante' colleague='http://www.ic.unicamp.br/MC536/2013/1/raphaelsantos'/><Knows person='http://www.ic.unicamp.br/MC536/2013/1/fernandohoyo' colleague='http://www.ic.unicamp.br/MC536/2013/1/davidchazanas'/><Knows person='http://www.ic.unicamp.br/MC536/2013/1/rafaelhermano' colleague='http://www.ic.unicamp.br/MC536/2013/1/alexandremedeiros'/><Knows person='http://www.ic.unicamp.br/MC536/2013/1/rafaelhermano' colleague='http://www.ic.unicamp.br/MC536/2013/1/brunocarvalho'/><Knows person='http://www.ic.unicamp.br/MC536/2013/1/rafaelhermano' colleague='http://www.ic.unicamp.br/MC536/2013/1/gabrielbertazi'/><Knows person='http://www.ic.unicamp.br/MC536/2013/1/rafaelhermano' colleague='http://www.ic.unicamp.br/MC536/2013/1/fabiosartorato'/><Knows person='http://www.ic.unicamp.br/MC536/2013/1/rafaelhermano' colleague='http://www.ic.unicamp.br/MC536/2013/1/raphaelsantos'/><Knows person='http://www.ic.unicamp.br/MC536/2013/1/rafaelhermano' colleague='http://www.ic.unicamp.br/MC536/2013/1/augustomorgan'/><Knows person='http://www.ic.unicamp.br/MC536/2013/1/rafaelhermano' colleague='http://www.ic.unicamp.br/MC536/2013/1/jonatanvalongo'/><Knows person='http://www.ic.unicamp.br/MC536/2013/1/andrepaganini' colleague='http://www.ic.unicamp.br/MC536/2013/1/paulorego'/><Knows person='http://www.ic.unicamp.br/MC536/2013/1/andrepaganini' colleague='http://www.ic.unicamp.br/MC536/2013/1/rafaelsacchi'/><Knows person='http://www.ic.unicamp.br/MC536/2013/1/andrepaganini' colleague='http://www.ic.unicamp.br/MC536/2013/1/luismendes'/><Knows person='http://www.ic.unicamp.br/MC536/2013/1/raphaelsantos' colleague='http://www.ic.unicamp.br/MC536/2013/1/amadeubonfante'/><Knows person='http://www.ic.unicamp.br/MC536/2013/1/raphaelsantos' colleague='http://www.ic.unicamp.br/MC536/2013/1/fabiosartorato'/><Knows person='http://www.ic.unicamp.br/MC536/2013/1/raphaelsantos' colleague='http://www.ic.unicamp.br/MC536/2013/1/gustavosilva'/><Knows person='http://www.ic.unicamp.br/MC536/2013/1/raphaelsantos' colleague='http://www.ic.unicamp.br/MC536/2013/1/andreborba'/><Knows person='http://www.ic.unicamp.br/MC536/2013/1/raphaelsantos' colleague='http://www.ic.unicamp.br/MC536/2013/1/emilioweber'/><Knows person='http://www.ic.unicamp.br/MC536/2013/1/raphaelsantos' colleague='http://www.ic.unicamp.br/MC536/2013/1/arthuralvarez'/><Knows person='http://www.ic.unicamp.br/MC536/2013/1/raphaelsantos' colleague='http://www.ic.unicamp.br/MC536/2013/1/viniciusana'/><Knows person='http://www.ic.unicamp.br/MC536/2013/1/luismendes' colleague='http://www.ic.unicamp.br/MC536/2013/1/andresantanche'/><Knows person='http://www.ic.unicamp.br/MC536/2013/1/luismendes' colleague='http://www.ic.unicamp.br/MC536/2013/1/andrepaganini'/><Knows person='http://www.ic.unicamp.br/MC536/2013/1/luismendes' colleague='http://www.ic.unicamp.br/MC536/2013/1/guilhermenunes'/><Knows person='http://www.ic.unicamp.br/MC536/2013/1/luismendes' colleague='http://www.ic.unicamp.br/MC536/2013/1/thiagopires'/><Knows person='http://www.ic.unicamp.br/MC536/2013/1/luismendes' colleague='http://www.ic.unicamp.br/MC536/2013/1/rafaelsacchi'/><Knows person='http://www.ic.unicamp.br/MC536/2013/1/luismendes' colleague='http://www.ic.unicamp.br/MC536/2013/1/marcelofabri'/><Knows person='http://www.ic.unicamp.br/MC536/2013/1/luismendes' colleague='http://www.ic.unicamp.br/MC536/2013/1/lucasmadureira'/><Knows person='http://www.ic.unicamp.br/MC536/2013/1/thiagopires' colleague='http://www.ic.unicamp.br/MC536/2013/1/alexandremedeiros'/><Knows person='http://www.ic.unicamp.br/MC536/2013/1/thiagopires' colleague='http://www.ic.unicamp.br/MC536/2013/1/marcelofabri'/><Knows person='http://www.ic.unicamp.br/MC536/2013/1/thiagopires' colleague='http://www.ic.unicamp.br/MC536/2013/1/rafaelsacchi'/><Knows person='http://www.ic.unicamp.br/MC536/2013/1/thiagopires' colleague='http://www.ic.unicamp.br/MC536/2013/1/guilhermenunes'/><Knows person='http://www.ic.unicamp.br/MC536/2013/1/thiagopires' colleague='http://www.ic.unicamp.br/MC536/2013/1/paulorego'/><Knows person='http://www.ic.unicamp.br/MC536/2013/1/thiagopires' colleague='http://www.ic.unicamp.br/MC536/2013/1/andrepaganini'/><Knows person='http://www.ic.unicamp.br/MC536/2013/1/thiagopires' colleague='http://www.ic.unicamp.br/MC536/2013/1/luismendes'/><Knows person='http://www.ic.unicamp.br/MC536/2013/1/thiagopires' colleague='http://www.ic.unicamp.br/MC536/2013/1/andresantanche'/><Knows person='http://www.ic.unicamp.br/MC536/2013/1/thiagopires' colleague='http://www.ic.unicamp.br/MC536/2013/1/renanfujii'/><Knows person='http://www.ic.unicamp.br/MC536/2013/1/thiagopires' colleague='http://www.ic.unicamp.br/MC536/2013/1/augustomorgan'/><Knows person='http://www.ic.unicamp.br/MC536/2013/1/thiagopires' colleague='http://www.ic.unicamp.br/MC536/2013/1/fabiosartorato'/><Knows person='http://www.ic.unicamp.br/MC536/2013/1/gabrielsarraff' colleague='http://www.ic.unicamp.br/MC536/2013/1/danielferreira'/><Knows person='http://www.ic.unicamp.br/MC536/2013/1/gabrielsarraff' colleague='http://www.ic.unicamp.br/MC536/2013/1/andresantanche'/><Knows person='http://www.ic.unicamp.br/MC536/2013/1/paulorego' colleague='http://www.ic.unicamp.br/MC536/2013/1/jonatanvalongo'/><Knows person='http://www.ic.unicamp.br/MC536/2013/1/paulorego' colleague='http://www.ic.unicamp.br/MC536/2013/1/andreborba'/><Knows person='http://www.ic.unicamp.br/MC536/2013/1/paulorego' colleague='http://www.ic.unicamp.br/MC536/2013/1/augustomorgan'/><Knows person='http://www.ic.unicamp.br/MC536/2013/1/gustavosilva' colleague='http://www.ic.unicamp.br/MC536/2013/1/andreborba'/><Knows person='http://www.ic.unicamp.br/MC536/2013/1/gustavosilva' colleague='http://www.ic.unicamp.br/MC536/2013/1/arthuralvarez'/><Knows person='http://www.ic.unicamp.br/MC536/2013/1/gustavosilva' colleague='http://www.ic.unicamp.br/MC536/2013/1/emilioweber'/><Knows person='http://www.ic.unicamp.br/MC536/2013/1/gustavosilva' colleague='http://www.ic.unicamp.br/MC536/2013/1/pedrofigueiredo'/><Knows person='http://www.ic.unicamp.br/MC536/2013/1/gustavosilva' colleague='http://www.ic.unicamp.br/MC536/2013/1/raphaelsantos'/><Knows person='http://www.ic.unicamp.br/MC536/2013/1/amadeubonfante' colleague='http://www.ic.unicamp.br/MC536/2013/1/andresantanche'/><Knows person='http://www.ic.unicamp.br/MC536/2013/1/amadeubonfante' colleague='http://www.ic.unicamp.br/MC536/2013/1/pedrofigueiredo'/><Knows person='http://www.ic.unicamp.br/MC536/2013/1/gustavosilva' colleague='http://www.ic.unicamp.br/MC536/2013/1/augustomorgan'/><Knows person='http://www.ic.unicamp.br/MC536/2013/1/gustavosilva' colleague='http://www.ic.unicamp.br/MC536/2013/1/fabiosartorato'/><Knows person='http://www.ic.unicamp.br/MC536/2013/1/thiagobalbo' colleague='http://www.ic.unicamp.br/MC536/2013/1/alexandrekunieda'/><Knows person='http://www.ic.unicamp.br/MC536/2013/1/thiagobalbo' colleague='http://www.ic.unicamp.br/MC536/2013/1/leonardoana'/><Knows person='http://www.ic.unicamp.br/MC536/2013/1/thiagobalbo' colleague='http://www.ic.unicamp.br/MC536/2013/1/fernandomassunari'/><Knows person='http://www.ic.unicamp.br/MC536/2013/1/thiagobalbo' colleague='http://www.ic.unicamp.br/MC536/2013/1/marcelozabani'/><Knows person='http://www.ic.unicamp.br/MC536/2013/1/thiagobalbo' colleague='http://www.ic.unicamp.br/MC536/2013/1/henriquegonzales'/><Knows person='http://www.ic.unicamp.br/MC536/2013/1/thiagobalbo' colleague='http://www.ic.unicamp.br/MC536/2013/1/andresantanche'/><Knows person='http://www.ic.unicamp.br/MC536/2013/1/guilhermeplatzeck' colleague='http://www.ic.unicamp.br/MC536/2013/1/alexandremedeiros'/><Knows person='http://www.ic.unicamp.br/MC536/2013/1/guilhermeplatzeck' colleague='http://www.ic.unicamp.br/MC536/2013/1/andreborba'/><Knows person='http://www.ic.unicamp.br/MC536/2013/1/guilhermeplatzeck' colleague='http://www.ic.unicamp.br/MC536/2013/1/davidchazanas'/><Knows person='http://www.ic.unicamp.br/MC536/2013/1/guilhermeplatzeck' colleague='http://www.ic.unicamp.br/MC536/2013/1/andresantanche'/><Knows person='http://www.ic.unicamp.br/MC536/2013/1/guilhermeplatzeck' colleague='http://www.ic.unicamp.br/MC536/2013/1/gabrielbertazi'/><Knows person='http://www.ic.unicamp.br/MC536/2013/1/guilhermeplatzeck' colleague='http://www.ic.unicamp.br/MC536/2013/1/gabrielsarraff'/><Knows person='http://www.ic.unicamp.br/MC536/2013/1/guilhermeplatzeck' colleague='http://www.ic.unicamp.br/MC536/2013/1/fernandohoyo'/><Knows person='http://www.ic.unicamp.br/MC536/2013/1/guilhermeplatzeck' colleague='http://www.ic.unicamp.br/MC536/2013/1/lucasmadureira'/><Knows person='http://www.ic.unicamp.br/MC536/2013/1/guilhermeplatzeck' colleague='http://www.ic.unicamp.br/MC536/2013/1/matheusboy'/><Knows person='http://www.ic.unicamp.br/MC536/2013/1/guilhermeplatzeck' colleague='http://www.ic.unicamp.br/MC536/2013/1/luismendes'/><Knows person='http://www.ic.unicamp.br/MC536/2013/1/guilhermeplatzeck' colleague='http://www.ic.unicamp.br/MC536/2013/1/renanfujii'/><Knows person='http://www.ic.unicamp.br/MC536/2013/1/guilhermeplatzeck' colleague='http://www.ic.unicamp.br/MC536/2013/1/rafaelsacchi'/><Knows person='http://www.ic.unicamp.br/MC536/2013/1/guilhermeplatzeck' colleague='http://www.ic.unicamp.br/MC536/2013/1/mariasousa'/><Knows person='http://www.ic.unicamp.br/MC536/2013/1/diegorubini' colleague='http://www.ic.unicamp.br/MC536/2013/1/andresantanche'/><Knows person='http://www.ic.unicamp.br/MC536/2013/1/raissamachado' colleague='http://www.ic.unicamp.br/MC536/2013/1/matheusboy'/><Knows person='http://www.ic.unicamp.br/MC536/2013/1/diegorubini' colleague='http://www.ic.unicamp.br/MC536/2013/1/brunocarvalho'/><Knows person='http://www.ic.unicamp.br/MC536/2013/1/diegorubini' colleague='http://www.ic.unicamp.br/MC536/2013/1/danielferreira'/><Knows person='http://www.ic.unicamp.br/MC536/2013/1/raissamachado' colleague='http://www.ic.unicamp.br/MC536/2013/1/diegorubini'/><Knows person='http://www.ic.unicamp.br/MC536/2013/1/raissamachado' colleague='http://www.ic.unicamp.br/MC536/2013/1/davidchazanas'/><Knows person='http://www.ic.unicamp.br/MC536/2013/1/diegorubini' colleague='http://www.ic.unicamp.br/MC536/2013/1/gabrielsarraff'/><Knows person='http://www.ic.unicamp.br/MC536/2013/1/raissamachado' colleague='http://www.ic.unicamp.br/MC536/2013/1/emilioweber'/><Knows person='http://www.ic.unicamp.br/MC536/2013/1/diegorubini' colleague='http://www.ic.unicamp.br/MC536/2013/1/igornunes'/><Knows person='http://www.ic.unicamp.br/MC536/2013/1/mariasousa' colleague='http://www.ic.unicamp.br/MC536/2013/1/emilioweber'/><Knows person='http://www.ic.unicamp.br/MC536/2013/1/raissamachado' colleague='http://www.ic.unicamp.br/MC536/2013/1/leonardoana'/><Knows person='http://www.ic.unicamp.br/MC536/2013/1/diegorubini' colleague='http://www.ic.unicamp.br/MC536/2013/1/ivanfilho'/><Knows person='http://www.ic.unicamp.br/MC536/2013/1/raissamachado' colleague='http://www.ic.unicamp.br/MC536/2013/1/fernandohoyo'/><Knows person='http://www.ic.unicamp.br/MC536/2013/1/diegorubini' colleague='http://www.ic.unicamp.br/MC536/2013/1/ivanfreitas'/><Knows person='http://www.ic.unicamp.br/MC536/2013/1/diegorubini' colleague='http://www.ic.unicamp.br/MC536/2013/1/lucaslima'/><Knows person='http://www.ic.unicamp.br/MC536/2013/1/raissamachado' colleague='http://www.ic.unicamp.br/MC536/2013/1/mariasousa'/><Knows person='http://www.ic.unicamp.br/MC536/2013/1/diegorubini' colleague='http://www.ic.unicamp.br/MC536/2013/1/luizjunior'/><Knows person='http://www.ic.unicamp.br/MC536/2013/1/diegorubini' colleague='http://www.ic.unicamp.br/MC536/2013/1/lucasnakata'/><Knows person='http://www.ic.unicamp.br/MC536/2013/1/raissamachado' colleague='http://www.ic.unicamp.br/MC536/2013/1/lucaslima'/><Knows person='http://www.ic.unicamp.br/MC536/2013/1/raissamachado' colleague='http://www.ic.unicamp.br/MC536/2013/1/danielferreira'/><Knows person='http://www.ic.unicamp.br/MC536/2013/1/diegorubini' colleague='http://www.ic.unicamp.br/MC536/2013/1/matheusboy'/><Knows person='http://www.ic.unicamp.br/MC536/2013/1/raissamachado' colleague='http://www.ic.unicamp.br/MC536/2013/1/amadeubonfante'/><Knows person='http://www.ic.unicamp.br/MC536/2013/1/diegorubini' colleague='http://www.ic.unicamp.br/MC536/2013/1/raissamachado'/><Knows person='http://www.ic.unicamp.br/MC536/2013/1/diegorubini' colleague='http://www.ic.unicamp.br/MC536/2013/1/renatovargas'/><Knows person='http://www.ic.unicamp.br/MC536/2013/1/raissamachado' colleague='http://www.ic.unicamp.br/MC536/2013/1/renatovargas'/><Knows person='http://www.ic.unicamp.br/MC536/2013/1/raissamachado' colleague='http://www.ic.unicamp.br/MC536/2013/1/rafaelgouvea'/></AllKnows>